heliumhelper/__init__.py
heliumhelper/helpers.py
heliumhelper-0.3.0.dist-info/WHEEL
heliumhelper-0.3.0.dist-info/METADATA
heliumhelper-0.3.0.dist-info/RECORD
